livejson.py
livejson-1.8.1.dist-info/DESCRIPTION.rst
livejson-1.8.1.dist-info/METADATA
livejson-1.8.1.dist-info/RECORD
livejson-1.8.1.dist-info/WHEEL
livejson-1.8.1.dist-info/metadata.json
livejson-1.8.1.dist-info/top_level.txt
