Metadata-Version: 2.0
Name: livejson
Version: 1.8.1
Summary: Bind Python objects to JSON files
Home-page: https://github.com/controversial/livejson/
Author: Luke Taylor
Author-email: luke@deentaylor.com
License: MIT
Keywords: livejson json io development file files live update
Platform: UNKNOWN
